__init__.py
abc.py
sfla.py
util.py
metaheuristic_clustering/__init__.py
metaheuristic_clustering/abc.py
metaheuristic_clustering/sfla.py
metaheuristic_clustering/util.py
metaheuristic_clustering-0.0.2.dist-info/METADATA
metaheuristic_clustering-0.0.2.dist-info/WHEEL
metaheuristic_clustering-0.0.2.dist-info/top_level.txt
metaheuristic_clustering-0.0.2.dist-info/RECORD
