Metadata-Version: 2.1
Name: metaheuristic-clustering
Version: 0.0.2
Summary: sklearn and pyclustering style implementations of SFLA and ABC
Home-page: https://github.com/ElizabethForest/metaheuristic_clustering
Author: Elizabeth Ditton
Author-email: elizabeth.forest@my.jcu.edu.au
License: UNKNOWN
Platform: UNKNOWN
Classifier: Programming Language :: Python :: 3
Classifier: Programming Language :: Python :: 3.7
Classifier: Programming Language :: Python :: 3.8
Classifier: Programming Language :: Python :: 3.9
Classifier: Intended Audience :: Science/Research
Classifier: Natural Language :: English
Classifier: Topic :: Scientific/Engineering
Classifier: Topic :: Scientific/Engineering :: Artificial Intelligence
Requires-Python: >=3.7
Requires-Dist: pyclustering
Requires-Dist: sklearn
Requires-Dist: numpy
